simplemathlib/__init__.py
simplemathlib/operations.py
simplemathlib-0.2.dist-info/METADATA
simplemathlib-0.2.dist-info/WHEEL
simplemathlib-0.2.dist-info/top_level.txt
simplemathlib-0.2.dist-info/RECORD
