Metadata-Version: 2.1
Name: simplemathlib
Version: 0.2
Summary: A simple math library
Home-page: https://github.com/yourusername/simplemathlib
Author: Your Name
Author-email: youremail@example.com
License: MIT
Classifier: Programming Language :: Python :: 3
Classifier: License :: OSI Approved :: MIT License
Classifier: Operating System :: OS Independent
Requires-Python: >=3.6
